{
	"id": "nether_basaltic_sands",
	"dimension": "nether",
	"type": "tfc:disc_vein",
	"config": {
		"rarity": 160,
		"density": 0.4,
		"min_y": 48,
		"max_y": 128,
		"size": 48,
		"height": 9
	},
	"ores": [
		{
			"ore": "basaltic_mineral_sand",
			"weight": 35,
			"block_weight": 1
		},
		{
			"ore": "granitic_mineral_sand",
			"weight": 25,
			"block_weight": 1
		},
		{
			"ore": "fullers_earth",
			"weight": 25,
			"block_weight": 1
		},
		{
			"ore": "gypsum",
			"weight": 15
		}
	],
	"rocks": [
		"granite",
		"basalt"
	],
	"indicator": {
		"depth": 1,
		"underground_count": 150
	},
	"translations": [
		{
			"lang": "en_us",
			"text": "Mineral Sands"
		},
		{
			"lang": "pt_br",
			"text": "Areias Minerais"
		},
		{
			"lang": "ru_ru",
			"text": "Минеральные пески"
		},
		{
			"lang": "uk_ua",
			"text": "Мінеральні піски"
		},
		{
			"lang": "zh_cn",
			"text": "矿砂"
		},
        {
            "lang": "de_de",
            "text": "Mineralsand"
        }
	]
}