{
  "metaitem.behavior.mode_switch.current_mode": "Mode: %s",
  "metaitem.behavior.mode_switch.mode_switched": "§eMode Set to: %s",
  "metaitem.behavior.mode_switch.tooltip": "Use while sneaking to switch mode",
  "metaitem.clipboard.tooltip": "Can be written on (without any writing Instrument). Right-click on Wall to place, and Shift-Right-Click to remove",
  "metaitem.cover.digital.mode.energy.disabled": "Click to enable Energy Mode",
  "metaitem.cover.digital.mode.energy.enabled": "Energy Mode enabled",
  "metaitem.cover.digital.mode.fluid.disabled": "Click to enable Fluid Mode",
  "metaitem.cover.digital.mode.fluid.enabled": "Fluid Mode enabled",
  "metaitem.cover.digital.mode.item.disabled": "Click to enable Item Mode",
  "metaitem.cover.digital.mode.item.enabled": "Item Mode enabled",
  "metaitem.cover.digital.mode.machine.disabled": "Click to enable Machine Mode",
  "metaitem.cover.digital.mode.machine.enabled": "Machine Mode enabled",
  "metaitem.cover.digital.mode.proxy.disabled": "Click to enable Proxy Mode",
  "metaitem.cover.digital.mode.proxy.enabled": "Proxy Mode enabled",
  "metaitem.cover.digital.tooltip": "Connects machines over §fPower Cables§7 to the §fCentral Monitor§7 as §fCover§7.",
  "metaitem.cover.digital.wireless.tooltip.0": "§fWirelessly§7 connects machines to the §fCentral Monitor§7 as §fCover§7.",
  "metaitem.cover.digital.wireless.tooltip.1": "§fRight Click§7 on the §fCentral Monitor§7 to remotely bind to it.",
  "metaitem.cover.digital.wireless.tooltip.2": "§fSneak Right Click§7 to remove the current binding.",
  "metaitem.cover.digital.wireless.tooltip.3": "§aBinding: §f%s",
  "metaitem.crushed.tooltip.purify": "Drop in Water to get Purified Ore",
  "metaitem.debug_scanner.tooltip": "Tricorder",
  "metaitem.dust.tooltip.purify": "Drop in Water to get Clean Dust",
  "metaitem.electric.discharge_mode.disabled": "§eDischarge Mode Disabled",
  "metaitem.electric.discharge_mode.enabled": "§eDischarge Mode Enabled",
  "metaitem.electric.discharge_mode.tooltip": "Use while sneaking to toggle discharge mode",
  "metaitem.generic.electric_item.stored": "%d/%d EU (%s)",
  "metaitem.generic.electric_item.tooltip": "%d/%d EU - Tier %s",
  "metaitem.generic.fluid_container.tooltip": "%d/%dL %s",
  "metaitem.int_circuit.configuration": "Configuration: %d",
  "metaitem.liquid_fuel_jetpack.tooltip": "Uses Combustion Generator Fuels for Thrust",
  "metaitem.machine_configuration.mode": "§aConfiguration Mode:§r %s",
  "metaitem.plugin.proxy.tooltips.1": "(Please adjust to proxy mode in the screen)",
  "metaitem.plugin.tooltips.1": "Plugins can be added to the screen for more functionality.",
  "metaitem.prospector.mode.bedrock_ore": "§bBedrock Ore Prospection Mode§r",
  "metaitem.prospector.mode.fluid": "§bFluid Prospection Mode§r",
  "metaitem.prospector.mode.ores": "§aOre Prospection Mode§r",
  "metaitem.prospector.tooltip.modes": "Available Modes:",
  "metaitem.prospector.tooltip.radius": "Scans range in a %s Chunk Radius",
  "metaitem.record.sus.tooltip": "§7Leonz - Among Us Drip",
  "metaitem.terminal.tooltip": "Sharp tools make good work",
  "metaitem.terminal.tooltip.creative": "§bCreative Mode",
  "metaitem.terminal.tooltip.hardware": "§aHardware: %d",
  "metaitem.tool.tooltip.durability": "§fDurability: §a%d / %d",
  "metaitem.tool.tooltip.primary_material": "§fMaterial: §e%s",
  "metaitem.tool.tooltip.rotor.efficiency": "Turbine Efficiency: §9%d%%",
  "metaitem.tool.tooltip.rotor.power": "Turbine Power: §9%d%%",
  "metaitem.tricorder_scanner.tooltip": "Tricorder"
}