{
    "block.greate.andesite_alloy_cogwheel": "基礎齒輪",
    "block.greate.andesite_alloy_crushing_wheel": "基礎粉碎輪",
    "block.greate.andesite_alloy_crushing_wheel_controller": "基礎粉碎輪控制器",
    "block.greate.andesite_alloy_encased_fan": "基礎鼓風機",
    "block.greate.andesite_alloy_gearbox": "基礎齒輪箱",
    "block.greate.andesite_alloy_mechanical_mixer": "基礎動力攪拌器",
    "block.greate.andesite_alloy_mechanical_press": "基礎動力衝壓機",
    "block.greate.andesite_alloy_mechanical_pump": "基礎動力泵",
    "block.greate.andesite_alloy_mechanical_saw": "基礎動力鋸",
    "block.greate.andesite_alloy_millstone": "基礎石磨",
    "block.greate.andesite_alloy_shaft": "基礎傳動軸",
    "block.greate.andesite_encased_aluminium_cogwheel": "金屬鋁裝殼齒輪",
    "block.greate.andesite_encased_aluminium_shaft": "金屬鋁裝殼傳動軸",
    "block.greate.andesite_encased_andesite_alloy_cogwheel": "金屬基礎裝殼齒輪",
    "block.greate.andesite_encased_andesite_alloy_shaft": "金屬基礎裝殼傳動軸",
    "block.greate.andesite_encased_large_aluminium_cogwheel": "金屬大型鋁裝殼齒輪",
    "block.greate.andesite_encased_large_andesite_alloy_cogwheel": "金屬大型基礎裝殼齒輪",
    "block.greate.andesite_encased_large_stainless_steel_cogwheel": "金屬大型不鏽鋼裝殼齒輪",
    "block.greate.andesite_encased_large_steel_cogwheel": "金屬大型鋼裝殼齒輪",
    "block.greate.andesite_encased_large_titanium_cogwheel": "金屬大型鈦裝殼齒輪",
    "block.greate.andesite_encased_stainless_steel_cogwheel": "金屬不鏽鋼裝殼齒輪",
    "block.greate.andesite_encased_stainless_steel_shaft": "金屬不鏽鋼裝殼傳動軸",
    "block.greate.andesite_encased_steel_cogwheel": "金屬鋼裝殼齒輪",
    "block.greate.andesite_encased_steel_shaft": "金屬鋼裝殼傳動軸",
    "block.greate.andesite_encased_titanium_cogwheel": "金屬鈦裝殼齒輪",
    "block.greate.andesite_encased_titanium_shaft": "金屬鈦裝殼傳動軸",
    "block.greate.brass_encased_andesite_alloy_cogwheel": "黃銅基礎裝殼齒輪",
    "block.greate.brass_encased_andesite_alloy_shaft": "黃銅基礎裝殼傳動軸",
    "block.greate.brass_encased_large_andesite_alloy_cogwheel": "黃銅大型基礎裝殼齒輪",
    "block.greate.large_andesite_alloy_cogwheel": "大型基礎齒輪",
    "block.greate.metal_girder_encased_andesite_alloy_shaft": "金屬梁裝殼基礎傳動軸",
    "block.greate.powered_andesite_alloy_shaft": "基礎動力傳動軸",
    "item.greate.andesite_alloy_belt_connector": "木板履帶傳送帶",
    "item.greate.stone_belt_connector": "皮革傳送帶",
    "item.greate.rubber_belt_connector": "橡膠傳送帶",
    "item.greate.silicone_rubber_belt_connector": "矽橡膠傳送帶",
    "item.greate.styrene_butadiene_rubber_belt_connector": "丁苯橡膠傳送帶",
    "item.greate.andesite_alloy_vertical_gearbox": "基礎垂直齒輪箱",
    "greate.recipe.packing": "焊接與壓縮",
    "greate.ponder.belt_casing.text_1": "你可以用黃銅或者金屬機殼裝飾你的傳送帶",
    "greate.ponder.cogwheel_casing.text_1": "黃銅機殼或金屬機殼可用於裝飾齒輪"
}