{
  "item.tfcambiental.burlap_cowl": "Burlap Cowl",
  "item.tfcambiental.burlap_pants": "Burlap Pants",
  "item.tfcambiental.burlap_shirt": "Burlap Shirt",
  "item.tfcambiental.burlap_shoes": "Burlap Shoes",
  "item.tfcambiental.house_tester": "House Tester",
  "item.tfcambiental.insulated_leather_boots": "Insulated Leather Boots",
  "item.tfcambiental.insulated_leather_hat": "Insulated Leather Hat",
  "item.tfcambiental.insulated_leather_pants": "Insulated Leather Pants",
  "item.tfcambiental.insulated_leather_tunic": "Insulated Leather Tunic",
  "item.tfcambiental.leather_apron": "Leather Apron",
  "item.tfcambiental.silk_cowl": "Silk Cowl",
  "item.tfcambiental.silk_pants": "Silk Pants",
  "item.tfcambiental.silk_shirt": "Silk Shirt",
  "item.tfcambiental.silk_shoes": "Silk Shoes",
  "item.tfcambiental.snowshoes": "Snow Shoes",
  "item.tfcambiental.straw_hat": "Straw Hat",
  "item.tfcambiental.wool_boots": "Wool Boots",
  "item.tfcambiental.wool_hat": "Wool Hat",
  "item.tfcambiental.wool_pants": "Wool Pants",
  "item.tfcambiental.wool_sweater": "Wool Sweater"
}